socket_rpc/__init__.py
socket_rpc/standalone_client.py
socket_rpc/standalone_server.py
socket_rpc-0.4.6.dist-info/METADATA
socket_rpc-0.4.6.dist-info/WHEEL
socket_rpc-0.4.6.dist-info/top_level.txt
socket_rpc-0.4.6.dist-info/RECORD
